MalmoPython.cpython-39-darwin.so
malmo/version.py
malmo/__init__.py
malmo/minecraft.py
malmo/Schemas/MissionHandlers.xsd
malmo/Schemas/MissionInit.xsd
malmo/Schemas/MinecraftItems.txt
malmo/Schemas/CMakeLists.txt
malmo/Schemas/MissionEnded.xsd
malmo/Schemas/items.json
malmo/Schemas/Types.xsd
malmo/Schemas/Mission.xsd.in
malmo/Schemas/MissionHandlers.xsd.in
malmo/Schemas/MinecraftBlocks.txt
malmo/Schemas/Mission.xsd
malmo/Schemas/links.xml
malmo/Schemas/Types.xsd.in
malmo/Schemas/MissionEnded.xsd.in
malmo/Schemas/MissionInit.xsd.in
malmo/.dylibs/libboost_thread.dylib
malmo/.dylibs/libboost_iostreams.dylib
malmo/.dylibs/libboost_regex.dylib
malmo/.dylibs/libboost_program_options.dylib
malmo/.dylibs/libzstd.1.5.2.dylib
malmo/.dylibs/libboost_filesystem.dylib
malmo/.dylibs/liblzma.5.dylib
malmo/.dylibs/libboost_python39.dylib
malmo/.dylibs/libboost_atomic.dylib
malmo/.dylibs/libboost_date_time.dylib
malmo/.dylibs/libboost_system.dylib
malmo/.dylibs/libboost_chrono.dylib
malmo/Minecraft/Minecraft_Client.launch
malmo/Minecraft/CMakeLists.txt
malmo/Minecraft/MinecraftForge-Credits.txt
malmo/Minecraft/Paulscode SoundSystem CodecIBXM License.txt
malmo/Minecraft/CREDITS-fml.txt
malmo/Minecraft/gradlew
malmo/Minecraft/launch_minecraft_in_background.py
malmo/Minecraft/Paulscode IBXM Library License.txt
malmo/Minecraft/build.gradle
malmo/Minecraft/README.txt
malmo/Minecraft/LICENSE-new.txt
malmo/Minecraft/gradlew.bat
malmo/Minecraft/launchClient.bat
malmo/Minecraft/launchClient.sh
malmo/Minecraft/forgegradle/net/minecraftforge/gradle/tasks/DownloadAssetsTask$GetAssetTask.class
malmo/Minecraft/forgegradle/net/minecraftforge/gradle/tasks/DownloadAssetsTask$1.class
malmo/Minecraft/forgegradle/net/minecraftforge/gradle/tasks/DownloadAssetsTask$Asset.class
malmo/Minecraft/forgegradle/net/minecraftforge/gradle/tasks/DownloadAssetsTask.class
malmo/Minecraft/forgegradle/net/minecraftforge/gradle/common/Constants$1.class
mbag_malmo-0.38.0.0.dist-info/RECORD
mbag_malmo-0.38.0.0.dist-info/WHEEL
mbag_malmo-0.38.0.0.dist-info/top_level.txt
mbag_malmo-0.38.0.0.dist-info/LICENSE.txt
mbag_malmo-0.38.0.0.dist-info/METADATA
